{"PESSOA": {"marques luz": 1}, "TEMPO": {"": 1, "91998a": 1, "tw/919928in": 1, "8e-t00/so6'bzh'lo": 1, "2157": 1, "17v/91998in": 1, "8e-to0/so6'vth'lo": 1, "-910z/tte-995'olt": 1, "9998": 4, "127": 1, "0000": 1, "8e-t00/so6'vzh'lo": 2, "9007": 1, "9toz/ite-995'obt": 1, "sows919e": 1, "8e-to0/so6'bzh'lo": 1, "*opi8u.109": 1, "o19/go": 1, "so19919": 1, "6107": 1, "b2//|qnd": 1, "0138": 1, "19939w073": 1, "*032/go": 1, "03b19u029": 1, "o1990": 1, "9to0z/lz7'0t": 1, "0007": 1, "0221": 1, "8007": 1, "1933www02": 1, "tv/91298w": 1, "9/1998|a|": 1, "197": 1, "2152": 1}, "LOCAL": {}, "ORGANIZACAO": {"551a1": 1, "8s": 1, "3a oy1si9ay 3a": 1, "8tol": 1, "8l": 1}, "JURISPRUDENCIA": {"7os su \u201c anbsanbng|y es": 1, "yenuis no 1ea\u00e1pooo": 1, "8e-t00/so6'vzh'lo": 1, "y e9 '' e66t 2p \u201c 999 ' 8 5u 197": 1, "7v/01922|in": 1, "b291bw09": 1}, "LEGISLACAO": {"999 ' 8 su 197 bp al a |l| /8": 1}}