{"PESSOA": {" roberto": 1, "jos\u00e9 pinheiro dos santos": 1, "jos\u00e9 azarias barbosa": 1, "jos\u00e9 eleomar barbosa": 2, "marques santos": 2, "carlos roberto": 1, "carlos james da silva batista": 1, "mario pereira dantas": 1, "alves da silva": 1, "2000-001064/201 silva": 1, "rocha soares": 1, "cristine lima": 1, "carlos roberto dos santos dias": 1}, "TEMPO": {"12 de abril de 2017": 1, "2017": 2, "27 de abn": 1, "2011": 1, "06 de setembro de 2017": 1, "27 de abril de 2011": 1, "1700": 1, "12 de abril": 1, "29 de agosto de 2017": 1, "11 de outubro de 2017": 1, "08 de setembro de 2017": 1, "1000": 1}, "LOCAL": {"estado de alagoas": 1, "rua s\u00e1": 1}, "ORGANIZACAO": {}, "JURISPRUDENCIA": {"12,200.184/0001-12": 1, "2000-016129-2013": 1, "2000-001833/2006": 1, "t00-n03073/2017": 1, "processo n 4799 3108/2016": 1, "n\u00ba 12200 ir4/0001-12": 1, "n\u00ba 12200 184/0001-12": 1, "731 016/0001-4": 1, "n\u00ba 521660 404-97": 1, "57425-000": 1}, "LEGISLACAO": {"n\u00ba 003 642 895-710": 1, "209 026 974-04": 1, "\u00ba t42017": 1}}