{"PESSOA": {"reis teixeira": 5, "almeida dos santos": 1, "xavier soares martins": 3, "almeida dos": 1, "alexandre ayres da costa": 3, "alves ribeiro": 1, "cavalcanti": 1, "anjos rocha nepomuceno": 1, "amorim bittencourt de ara\u00fajo": 2, "mauro gon\u00e7alves costa": 1, "lima de oliveira": 2, "carlos christian reis teixeira": 1}, "TEMPO": {"22/12/2018": 4, "1993": 12, "2002": 3, "1990": 3, "31 de dezembro de 2018": 2, "2018": 1, "sa\u00fade/27524": 3, "0120": 2, "2006": 1, "2013": 1, "19 de setembro de 2008": 1, "2000": 1, "\u00a3lo de 2018": 1, "13 de abril de 2018 63 o0118/2018": 1, "02 de mar\u00e7o de 2018": 3, "10 de novembro de 1997": 2, "23 de \u00ab abril de 2003": 1, "n.\u00ba 47 de 10 de agosto de 2015": 1, "decreto n.\u00ba 06 de 23 e janeiro de 2001.": 1, "18 de julho de 2016": 2, "portaria semarh n.\u00ba 122 de or de abril de 2016": 1, "13 de maio de 2016": 2, "23 de abril de 2003": 1, "10 de agosto de 2015": 2, "23 de janeiro de 2001": 1, "portaria semarh n.\u00ba 122 de o8 de abril de 2016": 1, "31 de julho de 2014": 1, "07 de julho de 2015": 1, "21 de setembro de 2015": 1, "12 de abril de 2018": 5, "10 de abril de 2018": 2, "sexta-feira 13 de abril de 2018": 1, "10.303.0205.4349": 1, "21 de dezembro de 2017": 1, "0100": 1, "06/04/2018": 1, "26 de fevereiro de 2018": 1, "26 de fevereiro 2018": 1, "28/09/2017": 2, "05 de outubro de 2006": 1, "17 de junho de 2014": 1, "14 de fevereiro de 2006": 1, "17/02/2014": 1}, "LOCAL": {"rua via secund\u00e1ria 3": 1, "distrito industrial": 1}, "ORGANIZACAO": {" de estado da sa\u00fade do estado de alagoas": 1, "secretaria de estado da sa\u00fade do estado de alagoas": 2, "bioci\u00eancias s.a": 1, "brasil ltda": 1, "secretaria df estado da sa\u00fade do estado de alagoas": 1}, "JURISPRUDENCIA": {"ai 7 /2017": 1, "5.752": 1, "processo n.\u00ba 23010- 00116/2018": 1, "processo n.\u00ba 23010- 00117/2018": 1, "12.200,259/0001-65": 1, "188/2018-sesau": 1, "2000.005706/2018": 1, "910,695.055-87": 1, ".0205,4349": 1, "2000-012107/2017": 1, "2000- 012107/2017": 1}, "LEGISLACAO": {"n.\u00ba 277.063.938-28": 1, "8.666": 1, "10.520": 1, "8.078": 1, "24 da lei 8.666": 1, "5\u00ba , & 3\u00ba , da lei n\u00ba 8.666,1993": 1, "lei complementar n\u00ba 123": 1, "65 da lei n\u00ba 8.666": 1, "67 da lei n\u00ba 8.666": 1, "70 de lei n\u00ba 8.666": 1, "artigos 12 , 13 , e 17 a 27 do c\u00f3digo de defesa do consumidor": 1, "lei n\u00ba 8.078": 2, "lei n\u00ba 8,666": 1, "lei n\u00ba 10.520": 1, "lei 12.846": 1, "decreto n\u00ba 4.054": 1, "87 , 1ii e iv da lei n\u00ba 8.666": 1, "lei n\u00ba 8.666": 3, "lei n\u00ba 6.161": 1, "78 da lei n\u00ba 8.666": 1, "77 da lei n\u00ba 8.666": 1, "lei n\u00ba 10,520": 1, "lei n\u00ba 7.397/2012": 2, "n.\u00ba 070/2018": 1, "5.965": 2, "leis delegadas de n.\u00ba 32": 2, "decreto n.\u00ba 49.419": 1, "instru\u00e7\u00e3o normativa srh/semarh n.\u00ba 01": 1, "decreto estadual n\u00ba 20.029": 2, "lei estadual n\u00ba 7.094 , artigo 22": 1, "n.\u00ba 068/2018": 1, "n.\u00ba 47": 1, "decreto n.\u00ba 06": 1, "decreto n.\u00ba 49419": 1, "instru\u00e7\u00e3o norr srh/semarh n.\u00ba 01": 1, "lei estadual 1\u00ba 7.094 , artigo 22": 1, "n.\u00ba 072/2018": 1, "37 da constitui\u00e7\u00e3o federal": 1, "artigo 35 , incisos v da lei federal de n\u00ba 13.019de": 1, "decreto estadual de n\u00ba 41.104": 1, "decreto de n\u00ba 43.859": 1, "artigo 35 , inciso v , al\u00edncas a , b , c , d , e , f , g e h da lei federal de n\u00ba 13.019 de 31 de ju- iho de 2014": 1, "n.\u00ba 56.994,502/0098-62": 1, "24 , inciso iv da lei federal n\u00ba 8.666/93": 1, "25 inciso 1 , lei federal n\u00ba 8.666/93": 1, "portaria gm/ms n\u00ba 204/07": 1, "2\u00ba da emenda constitucional n\u00ba 51": 1}}