{"PESSOA": {"gon\u00e7alves lima": 3, "fernandes lima": 2, "napole\u00e3o barbosa": 2, "jos\u00e9 carlos lyra": 3, "andr\u00e9 luiz gomes": 1, "thais lessa pontes silva": 1, "carlos alberto barros de ara\u00fajo": 2, "carlos alberto barros": 1, "gon\u00e7alves lima /1": 1, "nunes de lima": 1, "farias cunha": 1}, "TEMPO": {"": 1, "1718": 12, "04 de mar\u00e7o de 2016": 1, "1993": 7, "2002": 3, "1990": 1, "1108": 11, "11 de outubro de 2017": 1, "2017": 1, "23.6920.2124.2300.000": 1, "33.50.41": 2, "2006": 1, "2013": 2, "19 de setembro de 2008": 1, "2000": 1, "sexta-feira 6 de outubro de 2017": 1, "31/08/2017": 2, "03 de outubro de 2017": 3, "25/09/2017": 1, "27/09/2017": 1, "05 de setembro de 2017": 1, "09 a 11 de outubro de 2017": 1, "17/10/2017": 1, "20/10/2017": 1, "05 de outubro de 2017.": 1, "05/10/2017": 1, "09/10/2017": 1}, "LOCAL": {"estado de alagoas": 1}, "ORGANIZACAO": {"secretaria de estado do desenvolvimento econ\u00f4mico e turismo de alagoas": 1, "federa\u00e7\u00e3o das ind\u00fastrias do estado de alagoas": 1, "secretaria de estado do desenvolvimento economico e turismo": 3, "secretaria de estado do desenvolvimento econ\u00f4mico e turismo": 1}, "JURISPRUDENCIA": {"2900.00891/2017": 1, "processo n\u00ba 52534-289/2017": 1, "43.7194/2015": 1, "processo n\u00ba 52534-304/2017": 1, "2900-891/2017": 1, "processo administrativo n\u00ba 2900.1167/2017": 1, "processo administrativo n\u00ba 2900.1177/2017": 1}, "LEGISLACAO": {"n.\u00ba 114.175": 1, "lei n\u00ba 8.666": 4, "lei n\u00ba 10.520": 3, "lei n\u00ba 8.078": 1, "57 , 81\u00ba , da lei n\u00ba 8.666": 1, "24 da lei 8.666": 1, "5\u00ba , 8 3\u00ba , da lei n\u00ba 8.666": 1, "lei complementar n\u00ba 123": 1, "lei 12.846": 2, "decreto n\u00ba 4.054": 1, "87 , m e iv da lei n\u00ba 8.666": 1, "lei n\u00ba 6.161": 1, "lei federal n\u00ba 8.666/1993": 1, "lei n\u00ba 10.520/2002": 1, "lei n\u00ba 8.078/1990": 1, "lei n\u00ba 8.666/1993": 1, "lei n\u00ba 7.397/2012": 1, "n\u00ba 4.076/2008": 2, "43.794/2015": 1, "decreto n\u00ba 4.076/2008": 2, "decreto n.\u00ba 43.794/2015": 2}}