{"PESSOA": {"horacio da silva": 1, "maria de almeida": 1, "leixg da silva": 1, "antonio horacio da silva cabral": 2, "almeida fernandes wyszomirska": 2, "almeida fernandes": 1, "gustavo paiva": 1, "jorge silva lira": 1}, "TEMPO": {"13/11/2014": 1, "n\u00ba101/2015": 1, "n\u00ba101/2615-": 1, "9s037.,96,99": 1, "20ul-2ml": 1, "n\u00ba101/2015-": 1, "3500": 2, "2200:1": 2, "2015": 2, "10.305.d238.4044.000": 1, "31 de dezembro de 2015": 1, "2014": 2, "26 de oow de 20 u": 1, "1622": 1, "72,5-116": 1, "sexta-feira": 1, "agosto de 2015": 2, "0120": 1, "10 de maio de 2012": 1, "26 de agosto de 2015": 1, "31 de dezembr de 2015": 1, "21 de fevereiro de 2002": 1, "24/08/2015": 1, "309.846.294-9": 1, "29/12/2014": 1, "2789": 1, "10 de agosto de 2015": 1, "3315-3295. de agosto de 2015": 1}, "LOCAL": {"estado de alagoas": 1}, "ORGANIZACAO": {"laboratorios ltda": 1}, "JURISPRUDENCIA": {"0.935.689/0002-27": 1, "06785-400": 1, "processo n.\u00ba 2000/8819/2014-cont": 1, "processo n.\u00ba 2000/8819/2014-con": 5, "8421.29.90": 1, "s077.90.59": 1, "8505.11.00": 2, "processo n.\u00ba 2000/8819/2014-contrato n\u00ba101/2015": 1, "processo n.\u00ba 2000/8819/2014-conftrato n\u00ba101/2015/sesau/al": 1, "100-120/200-240v": 1, "8474.39.00": 1, "2000/8819/2014-conitrato n\u00ba101/2015-sesau/al": 1, "13.1.4": 1, "b7/1991": 1, "n\u00ba 2000-8819/2014": 1, "processo n.\u00ba 2000/8819/2014-contrato n\u00ba101/2015-": 1, "2000/4798/2015": 1, "2000-19686/2012": 1, "sesau-017/2014": 1}, "LEGISLACAO": {" 101/2015": 1, "n.\u00ba 2000/8819/2014-cont|": 1, "lei n\u00ba 8.666/93": 1, "73 , inciso ll e pas": 1, "n.\u00ba 2000/8819/2014-cont": 1, "n.\u00ba 2090/8819/": 1, "lei estadual n\u00ba 6.539/2004": 2, "decreto estadual n\u00ba 4 11.1.1": 1, "artigos 77 a 80 da lei n.\u00ba 8.666": 1, "lei federal n\u00ba 10.520/2002": 1, "lei complementar n\u00ba 123/2006": 1, "decreto estadual n\u00ba 4.054/2008": 1, "lei federal n\u00ba 8.666/1993": 1, "lei 13.1.6": 1, "lei federal n\u00ba 8.078/1990": 1, "1.424/2003": 1, "decreto estadual n\u00ba 4.123/2009": 1, "n.\u00ba 2000/8819/2014-con": 1, "lei n\u00ba 7,397/2012": 1, "31 de dezembro de 2015 2000 / 6565 / 2015": 1}}