{"PESSOA": {"cl\u00e1udio alexandre ayres da costa": 4, "carlos jorge ferreira": 2, "ver\u00f4nica de lima": 2, "alexandre ayres da costa": 1, "carlos jorge": 1, "luciana lima": 3, "luciana lima de": 1, "lima": 1}, "TEMPO": {"1993": 11, "2002": 3, "31 de dezembro de 2019": 2, "2019": 1, "0220": 2, "0120": 2, "2006": 1, "1990": 2, "2013": 1, "19 de setembro de 2008": 1, "2000": 1, "2019.": 1, "ww\u00e1\u00e1_qk": 1, "ter\u00e7a-feira 19 de mar\u00e7o de 2019": 1, "18 de mar\u00e7o 2019": 1, "segunda": 4, "sexta-feira": 3, "18 de mar\u00e7o de 2019": 2, "18 de mar\u00e7o 2019.": 1, "7 de mar\u00e7o de 2019": 1, "10 de agosto de 2015": 1, "11 de agosto de 2015": 1, "8 de janeiro de 2016": 1, "12 de janeiro de 2016": 1, "15 de mar\u00e7o de 2019": 2, "30 de janeiro de 2019": 1, "14 de mar\u00e7o de 2019": 1}, "LOCAL": {}, "ORGANIZACAO": {" de estado da sa\u00fade do estado de alagoas": 1, "secretaria de estado da sa\u00fade": 1, "secretaria de estado da sa\u00fade do estado de alagoas": 1}, "JURISPRUDENCIA": {"259/0001-65": 1, "22.554.493.0001-44": 1, "79 ) .3025.9988": 2, "2000- 023251/2017": 1, "059/2019_*": 1, "57025-050": 4, "2000/3512/2019": 1, "2000/4286/2015": 1, "82-3315-1142": 1, "2000/26198/2018": 1, "059/2019-sesau": 1, "2000.023251/2017": 1, "22.554.493,0001-44": 1, "2000-001768/2019": 1, "apenso n\u00ba 2000-001121/2019": 1}, "LEGISLACAO": {"8.666": 1, "10.520": 1, "8.078": 1, "1990 10.479/2018": 1, "24 da lei 8.666": 1, "5\u00ba , & 3\u00ba , da lei n\u00ba 8.666,1993": 1, "lei complementar n\u00ba 123": 1, "65 da lei n\u00ba 8.666": 1, "jorge de lima 10.479/2018 10.479/2018": 1, "67 da lei n\u00ba 8.666": 1, "70 de lei n\u00ba 8.666": 1, "1993 10.479/2018 10.479/2018 10.479/2018 10.479/2018 10.479/2018": 1, "artigos 12 , 13 , e 17 a 27 do c\u00f3digo de defesa do consumidor": 1, "lei n\u00ba 8.078": 2, "lei n\u00ba 8.666": 4, "lei n\u00ba 10.520": 2, "lei 12.846": 1, "decreto n\u00ba 4.054": 1, "87 , iii e iv da lei n\u00ba 8.666": 1, "lei n\u00ba 6.161": 1, "78 da lei n\u00ba 8.666": 1, "77 da lei n\u00ba 8.666": 1, "lei n\u00ba 7,397/2012": 1, "artigo 36": 1, "lei federal n\u00ba 8.666/93": 1, "61 , do decreto n\u00ba 63.847": 1}}