{"PESSOA": {"xavier martins": 4, "reis teixeira": 2, "fabio coser silva": 1}, "TEMPO": {"08/06/2019": 1, "1993": 11, "31 de dezembro de 2018": 3, "2018": 2, "2006": 1, "2002": 2, "2013": 1, "19 de setembro de 2008.": 1, "1993.": 1, "1990": 1, "qb de 2018": 1, "17 de agosto de 2018": 1, "14 de agosto de 2018": 2, "1211": 1, "09 de agosto de": 1, "10.302.0205.4347": 1, "09 de agosto de 2018": 3, "2315": 1, "115091-4000": 1, "1905": 1}, "LOCAL": {"rio de janeiro": 1}, "ORGANIZACAO": {"brasil ltda": 2, "reis teixeira do brasil ltda": 1, "kycharsky": 1, "reis teixeira estado da do brasil ltda": 1, "secretaria de estado da sa\u00fade do estado de alagoas": 1}, "JURISPRUDENCIA": {"": 1, "115091-4000": 1, "2000-0011392/2018": 1, "2000.010361/2018": 1, "2000.011392/2018": 1, "11,368/2017": 1, "2000.001392/2018": 1, "98870-6080": 1, "10.303.0205,4349": 1}, "LEGISLACAO": {"8.078": 1, "8.666": 1, "10.520": 1, "2002 11.368/2017": 1, "24 da lei 8.666": 1, "arti|59 , & 3\u00ba , da lei n\u00ba 8.666,1993": 1, "67 da lei n\u00ba 8.666": 1, "70 de lei n\u00ba 8.666": 1, "artigos 12 , 13 , 1990": 1, "17 a 27 do c\u00f3digo de defesa do consumidor": 1, "lei n\u00ba 8.078": 1, "lei n\u00ba 8.666": 3, "lei n\u00ba & ha lei 12.846": 1, "87 , 111 e iv da lei n\u00ba 8.666": 1, "lei n\u00ba 6.161": 1, "77 da lei n\u00ba 8.666": 1, "lei n de licita\u00e7\u00f5es e c contidas|na lei n princ\u00edpio : ra ' l/sd": 1, "disposi\u00e7\u00f5es 8.666": 1, "lei n\u00ba 10.520": 1, "lei n\u00ba 7.397/2012": 1, "18 , da amgesp , lei federal n\u00ba 018": 1, "lei federal n\u00ba 8.666/93": 2, "l\u00facia machado mattos 10.461/2017": 1}}